nqgreenapi/__init__.py
nqgreenapi/callback.py
nqgreenapi/exceptions.py
nqgreenapi/message.py
nqgreenapi/provider.py
nqgreenapi/quotas.py
nqgreenapi/resources/config_schema.json
nqgreenapi/serializers.py
nqgreenapi/utils.py
nqgreenapi-1.0.0a4.dist-info/LICENSE
nqgreenapi-1.0.0a4.dist-info/METADATA
nqgreenapi-1.0.0a4.dist-info/WHEEL
nqgreenapi-1.0.0a4.dist-info/RECORD
